{
    "dererers":["https://href.li/?","https://href.li/?","https://href.li/?","https://href.li/?"],
    "source":["facebook","instagram","google","vk"],
    "videos":
    [
        

        {"name":"Tulips flower garden / tulleys tulip farm uk / tulip garden london","Channel":"gamet","link":"https://client.ytmonster.net/frame/nO34y14EkX8","jump":"straight","secs":120},         
        {"name":"Bibury village england | the cotswolds | visit cotswolds | beautiful village vlog | Arlington row","Channel":"gamet","link":"https://client.ytmonster.net/frame/jXOYsisFxlI","jump":"straight","secs":120},         
        {"name":"Cotswold England / broadway tower / international travel vlog / England village life uk travel vlog","Channel":"gamet","link":"https://client.ytmonster.net/frame/DFRpO2O_nJ4","jump":"straight","secs":120},         
        {"name":"Titanic in tamil / funny dubbing video / tamil dubbin","Channel":"gamet","link":"https://client.ytmonster.net/frame/gbBIM6zc_mg","jump":"straight","secs":120},         
        {"name":"Cotswold England / international travel vlog / beautiful villages / England village life","Channel":"gamet","link":"https://client.ytmonster.net/frame/d9Ccg_iNllI","jump":"straight","secs":400},      
        {"name":"Farm shop reading / wellington farm shop / shops near reading","Channel":"gamet","link":"https://client.ytmonster.net/frame/S5ir9-zwBR0","jump":"straight","secs":420},      
        {"name":"Tulips flower garden / tulleys tulip farm uk / tulip garden london","Channel":"gamet","link":"https://client.ytmonster.net/frame/nO34y14EkX8","jump":"straight","secs":120},         
        {"name":"Abergavenny Museum / Museum #wales #england #uk #museum #travel #villagelife Castle in wales #castle ","Channel":"gamet","link":"https://client.ytmonster.net/frame/6PRktqhRMwk","jump":"straight","secs":420},      
        {"name":"ikea england / Ikea reading /ikea theale #ikea ","Channel":"gamet","link":"https://client.ytmonster.net/frame/5ZLevpNLvv0","jump":"straight","secs":700},      
        {"name":"Farm shop reading / wellington farm shop / shops near reading","Channel":"gamet","link":"https://client.ytmonster.net/frame/S5ir9-zwBR0","jump":"straight","secs":420},      
        {"name":"Trip to swiss | Trip to Lauterbrunen  | Lauterbrunen  | Swiss travel (Part 3)","Channel":"gamet","link":"https://client.ytmonster.net/frame/dAIL5C0eoxs","jump":"straight","secs":300},  
        {"name":"Killing The butcher in COD ","Channel":"gamet","link":"https://client.ytmonster.net/frame/SZ9lKSGpB9g","jump":"straight","secs":300},    
        {"name":"Bibury village england | the cotswolds | visit cotswolds | beautiful village vlog | Arlington row","Channel":"gamet","link":"https://client.ytmonster.net/frame/jXOYsisFxlI","jump":"straight","secs":120},         
        {"name":"Desperado vs The Butcher  ","Channel":"gamet","link":"https://client.ytmonster.net/frame/zPx9VW_KB7c","jump":"straight","secs":120},    
        {"name":"Tulips flower garden / tulleys tulip farm uk / tulip garden london","Channel":"gamet","link":"https://client.ytmonster.net/frame/nO34y14EkX8","jump":"straight","secs":120},         
        {"name":"TRANSFORMERS  Fall of Cybertron","Channel":"gamet","link":"https://client.ytmonster.net/frame/9yUH8Loycnk","jump":"straight","secs":120},      
        {"name":"Farm shop reading / wellington farm shop / shops near reading","Channel":"gamet","link":"https://client.ytmonster.net/frame/S5ir9-zwBR0","jump":"straight","secs":420},      
        {"name":"Titanic in tamil / funny dubbing video / tamil dubbin","Channel":"gamet","link":"https://client.ytmonster.net/frame/gbBIM6zc_mg","jump":"straight","secs":120},         
        {"name":"Nanban 3idiots mix / Indian movie remix","Channel":"gamet","link":"https://client.ytmonster.net/frame/WmV0x41hYLw","jump":"straight","secs":80},
        {"name":"Call of duty snowfight","Channel":"gamet","link":"https://client.ytmonster.net/frame/VlqeXosvpmU","jump":"straight","secs":180},    
        {"name":"Zombie highway gameplay ","Channel":"gamet","link":"https://client.ytmonster.net/frame/jB8u8cYeHNs","jump":"straight","secs":580},    
        {"name":"CODM Prizefighters","Channel":"gamet","link":"https://client.ytmonster.net/frame/MkdnKdUtJuo","jump":"straight","secs":180},         
        {"name":"Rytec AMR sniper | CODM Sniper | CODM gameplay sniper","Channel":"gamet","link":"https://client.ytmonster.net/frame/OTgE3ncuezE","jump":"straight","secs":100},    
        {"name":"CODM MX9 heartless | CODM special weapon | Call of duty mobile | MX9 heartless","Channel":"gamet","link":"https://client.ytmonster.net/frame/SxBkzjSOjl4","jump":"straight","secs":110},    
        {"name":"into the dead 2 | Arc 12 vanguard | Into the dead | Zombie games | Zombie","Channel":"gamet","link":"https://client.ytmonster.net/frame/LfKp_DaoN3k","jump":"straight","secs":180},         
        {"name":"Titanic in tamil / funny dubbing video / tamil dubbin","Channel":"gamet","link":"https://client.ytmonster.net/frame/gbBIM6zc_mg","jump":"straight","secs":120},         
        {"name":"Bibury village england | the cotswolds | visit cotswolds | beautiful village vlog | Arlington row","Channel":"gamet","link":"https://client.ytmonster.net/frame/jXOYsisFxlI","jump":"straight","secs":120},         
        {"name":"ikea england / Ikea reading /ikea theale #ikea ","Channel":"gamet","link":"https://client.ytmonster.net/frame/5ZLevpNLvv0","jump":"straight","secs":700},      
        {"name":"Beautiful village in england / castle combe village / natural beauty #travel #england","Channel":"gamet","link":"https://client.ytmonster.net/frame/YIMSMmuvZvA","jump":"straight","secs":300},      
        {"name":"Tulips flower garden / tulleys tulip farm uk / tulip garden london","Channel":"gamet","link":"https://client.ytmonster.net/frame/nO34y14EkX8","jump":"straight","secs":120},         
        {"name":"Call of Duty Cranked confirmed | Cranked confirmed | COD Cranked confirmed| Dog tag","Channel":"gamet","link":"https://client.ytmonster.net/frame/DXiEfZNrCN0","jump":"straight","secs":160},
        {"name":"Cotswold England / broadway tower / international travel vlog / England village life uk travel vlog","Channel":"gamet","link":"https://client.ytmonster.net/frame/DFRpO2O_nJ4","jump":"straight","secs":120},         
        {"name":"Farm shop reading / wellington farm shop / shops near reading","Channel":"gamet","link":"https://client.ytmonster.net/frame/S5ir9-zwBR0","jump":"straight","secs":420},      
        {"name":"COD New vision city | Call of duty mobile new map | call of Duty season","Channel":"gamet","link":"https://client.ytmonster.net/frame/BkjjNamgOjk","jump":"straight","secs":540},
        {"name":"Little venice","Channel":"gamet","link":"https://client.ytmonster.net/frame/uoyF8lVuU2o","jump":"straight","secs":70},
        {"name":"Zombie highway gameplay ","Channel":"gamet","link":"https://client.ytmonster.net/frame/jB8u8cYeHNs","jump":"straight","secs":580},    
        {"name":"Nanban 3idiots mix / Indian movie remix","Channel":"gamet","link":"https://client.ytmonster.net/frame/WmV0x41hYLw","jump":"straight","secs":80},
        {"name":"CODM Prizefighters","Channel":"gamet","link":"https://client.ytmonster.net/frame/MkdnKdUtJuo","jump":"straight","secs":180},    
        {"name":"Titanic in tamil / funny dubbing video / tamil dubbin","Channel":"gamet","link":"https://client.ytmonster.net/frame/gbBIM6zc_mg","jump":"straight","secs":120},         
        {"name":"Cotswold England / international travel vlog / beautiful villages / England village life","Channel":"gamet","link":"https://client.ytmonster.net/frame/d9Ccg_iNllI","jump":"straight","secs":400},      
        {"name":"Cotswold England / broadway tower / international travel vlog / England village life uk travel vlog","Channel":"gamet","link":"https://client.ytmonster.net/frame/DFRpO2O_nJ4","jump":"straight","secs":120},         
        {"name":"Rytec AMR sniper | CODM Sniper | CODM gameplay sniper","Channel":"gamet","link":"https://client.ytmonster.net/frame/OTgE3ncuezE","jump":"straight","secs":100},         
        {"name":"Bibury village england | the cotswolds | visit cotswolds | beautiful village vlog | Arlington row","Channel":"gamet","link":"https://client.ytmonster.net/frame/jXOYsisFxlI","jump":"straight","secs":120},         
        {"name":"Tulips flower garden / tulleys tulip farm uk / tulip garden london","Channel":"gamet","link":"https://client.ytmonster.net/frame/nO34y14EkX8","jump":"straight","secs":120},         
        {"name":"CODM MX9 heartless | CODM special weapon | Call of duty mobile | MX9 heartless","Channel":"gamet","link":"https://client.ytmonster.net/frame/SxBkzjSOjl4","jump":"straight","secs":110},    
        {"name":"Farm shop reading / wellington farm shop / shops near reading","Channel":"gamet","link":"https://client.ytmonster.net/frame/S5ir9-zwBR0","jump":"straight","secs":420},           
        {"name":"into the dead 2 | Arc 12 vanguard | Into the dead | Zombie games | Zombie","Channel":"gamet","link":"https://client.ytmonster.net/frame/LfKp_DaoN3k","jump":"straight","secs":180},      
        {"name":"Titanic in tamil / funny dubbing video / tamil dubbin","Channel":"gamet","link":"https://client.ytmonster.net/frame/gbBIM6zc_mg","jump":"straight","secs":120},         
        {"name":"Call of Duty Cranked confirmed | Cranked confirmed | COD Cranked confirmed| Dog tag","Channel":"gamet","link":"https://client.ytmonster.net/frame/DXiEfZNrCN0","jump":"straight","secs":160},
        {"name":"Cotswold England / broadway tower / international travel vlog / England village life uk travel vlog","Channel":"gamet","link":"https://client.ytmonster.net/frame/DFRpO2O_nJ4","jump":"straight","secs":120},         
        {"name":"Farm shop reading / wellington farm shop / shops near reading","Channel":"gamet","link":"https://client.ytmonster.net/frame/S5ir9-zwBR0","jump":"straight","secs":420},      
        {"name":"Beautiful village in england / castle combe village / natural beauty #travel #england","Channel":"gamet","link":"http://bit.ly/3TEaveS","jump":"straight","secs":300},      
        {"name":"ikea england / Ikea reading /ikea theale #ikea ","Channel":"gamet","link":"https://client.ytmonster.net/frame/5ZLevpNLvv0","jump":"straight","secs":700},             
        {"name":"Cotswold England / broadway tower / international travel vlog / England village life uk travel vlog","Channel":"gamet","link":"https://client.ytmonster.net/frame/DFRpO2O_nJ4","jump":"straight","secs":120},         
        {"name":"Tulips flower garden / tulleys tulip farm uk / tulip garden london","Channel":"gamet","link":"https://client.ytmonster.net/frame/nO34y14EkX8","jump":"straight","secs":120},         
        {"name":"COD New vision city | Call of duty mobile new map | call of Duty season","Channel":"gamet","link":"https://client.ytmonster.net/frame/BkjjNamgOjk","jump":"straight","secs":540},
        {"name":"Bibury village england | the cotswolds | visit cotswolds | beautiful village vlog | Arlington row","Channel":"gamet","link":"https://client.ytmonster.net/frame/jXOYsisFxlI","jump":"straight","secs":120},         
        {"name":"Little venice","Channel":"gamet","link":"https://client.ytmonster.net/frame/uoyF8lVuU2o","jump":"straight","secs":70},
        {"name":"Avatar kiri","Channel":"gamet","link":"https://client.ytmonster.net/frame/PIGv37_TKp4","jump":"straight","secs":70},
        {"name":"Leo in Avatar","Channel":"gamet","link":"https://client.ytmonster.net/frame/fLHf9523Vc8","jump":"straight","secs":120},
        {"name":"Trip to swiss | Trip to Lauterbrunen  | Lauterbrunen  | Swiss travel (Part 3)","Channel":"gamet","link":"https://client.ytmonster.net/frame/dAIL5C0eoxs","jump":"straight","secs":300},  
        {"name":"Cotswold England / broadway tower / international travel vlog / England village life uk travel vlog","Channel":"gamet","link":"https://client.ytmonster.net/frame/DFRpO2O_nJ4","jump":"straight","secs":120},         
        {"name":"Killing The butcher in COD ","Channel":"gamet","link":"https://client.ytmonster.net/frame/SZ9lKSGpB9g","jump":"straight","secs":300},    
        {"name":"Desperado vs The Butcher  ","Channel":"gamet","link":"https://client.ytmonster.net/frame/zPx9VW_KB7c","jump":"straight","secs":120},    
        {"name":"Farm shop reading / wellington farm shop / shops near reading","Channel":"gamet","link":"https://client.ytmonster.net/frame/S5ir9-zwBR0","jump":"straight","secs":420},      
        {"name":"Tulips flower garden / tulleys tulip farm uk / tulip garden london","Channel":"gamet","link":"https://client.ytmonster.net/frame/nO34y14EkX8","jump":"straight","secs":120},         
        {"name":"TRANSFORMERS  Fall of Cybertron","Channel":"gamet","link":"https://client.ytmonster.net/frame/9yUH8Loycnk","jump":"straight","secs":120},    
        {"name":"Nanban 3idiots mix / Indian movie remix","Channel":"gamet","link":"https://client.ytmonster.net/frame/WmV0x41hYLw","jump":"straight","secs":80},   
        {"name":"Call of duty snowfight","Channel":"gamet","link":"https://client.ytmonster.net/frame/VlqeXosvpmU","jump":"straight","secs":180},    
        {"name":"Zombie highway gameplay ","Channel":"gamet","link":"https://client.ytmonster.net/frame/jB8u8cYeHNs","jump":"straight","secs":580},    
        {"name":"CODM Prizefighters","Channel":"gamet","link":"https://client.ytmonster.net/frame/MkdnKdUtJuo","jump":"straight","secs":180},    
        {"name":"Cotswold England / international travel vlog / beautiful villages / England village life","Channel":"gamet","link":"https://client.ytmonster.net/frame/d9Ccg_iNllI","jump":"straight","secs":400},      
        {"name":"call of duty mobile | night vision | team deathmatch night vision | CODM | COD","Channel":"gamet","link":"https://client.ytmonster.net/frame/RNo1qvTPRvo","jump":"straight","secs":160},    
        {"name":"Rytec AMR sniper | CODM Sniper | CODM gameplay sniper","Channel":"gamet","link":"https://client.ytmonster.net/frame/OTgE3ncuezE","jump":"straight","secs":100},    
        {"name":"Tulips flower garden / tulleys tulip farm uk / tulip garden london","Channel":"gamet","link":"https://client.ytmonster.net/frame/nO34y14EkX8","jump":"straight","secs":120},         
        {"name":"CODM MX9 heartless | CODM special weapon | Call of duty mobile | MX9 heartless","Channel":"gamet","link":"https://client.ytmonster.net/frame/SxBkzjSOjl4","jump":"straight","secs":110},        
        {"name":"into the dead 2 | Arc 12 vanguard | Into the dead | Zombie games | Zombie","Channel":"gamet","link":"https://client.ytmonster.net/frame/LfKp_DaoN3k","jump":"straight","secs":180},     
        {"name":"Farm shop reading / wellington farm shop / shops near reading","Channel":"gamet","link":"https://client.ytmonster.net/frame/S5ir9-zwBR0","jump":"straight","secs":420},      
        {"name":"Call of Duty Cranked confirmed | Cranked confirmed | COD Cranked confirmed| Dog tag","Channel":"gamet","link":"https://client.ytmonster.net/frame/DXiEfZNrCN0","jump":"straight","secs":160}, 
        {"name":"COD New vision city | Call of duty mobile new map | call of Duty season","Channel":"gamet","link":"https://client.ytmonster.net/frame/BkjjNamgOjk","jump":"straight","secs":540},    
        {"name":"Little venice","Channel":"gamet","link":"https://client.ytmonster.net/frame/uoyF8lVuU2o","jump":"straight","secs":70},
        {"name":"Zombie highway gameplay ","Channel":"gamet","link":"https://client.ytmonster.net/frame/jB8u8cYeHNs","jump":"straight","secs":580},    
        {"name":"Cotswold England / international travel vlog / beautiful villages / England village life","Channel":"gamet","link":"https://client.ytmonster.net/frame/d9Ccg_iNllI","jump":"straight","secs":400},      
        {"name":"Farm shop reading / wellington farm shop / shops near reading","Channel":"gamet","link":"https://client.ytmonster.net/frame/S5ir9-zwBR0","jump":"straight","secs":420},          
        {"name":"Nanban 3idiots mix / Indian movie remix","Channel":"gamet","link":"https://client.ytmonster.net/frame/WmV0x41hYLw","jump":"straight","secs":80}
        
    ]}